{
  "/(protected)/staff/activity/[activityId]/page": "app/(protected)/staff/activity/[activityId]/page.js",
  "/(protected)/staff/activity/page": "app/(protected)/staff/activity/page.js",
  "/(protected)/student/activity/[activityId]/evaluate/page": "app/(protected)/student/activity/[activityId]/evaluate/page.js",
  "/(protected)/student/activity/[activityId]/page": "app/(protected)/student/activity/[activityId]/page.js",
  "/(protected)/student/activityenroll/page": "app/(protected)/student/activityenroll/page.js",
  "/(protected)/student/myactivities/page": "app/(protected)/student/myactivities/page.js",
  "/(public)/auth/profile/page": "app/(public)/auth/profile/page.js",
  "/(public)/auth/signin/page": "app/(public)/auth/signin/page.js",
  "/favicon.ico/route": "app/favicon.ico/route.js"
}